[
  {
    "id": 0,
    "nome": "Nero Lucente",
    "info": "Un design audace che evoca eleganza e forza.",
    "hiddenInfo": "Testo Nascosto",
    "path": "/1",
    "imageUrl": "./image/glasses/glasses4.png"
  },
  {
    "id": 1,
    "nome": "Oro Luminoso",
    "info": "L'unione perfetta di stile raffinato e modernità.",
    "hiddenInfo": "Testo Nascosto",
    "path": "/2",
    "imageUrl": "./image/glasses/glasses2.png"
  },
  {
    "id": 2,
    "nome": "Titanio Raffinato",
    "info": "Una fusione di tecnologia avanzata e design futuristico.",
    "hiddenInfo": "Testo Nascosto",
    "path": "/3",
    "imageUrl": "./image/glasses/glasses1.png"
  },
  {
    "id": 3,
    "nome": "Vetro Cristallino",
    "info": "Semplicità sofisticata con una visione chiara e pura.",
    "hiddenInfo": "Testo Nascosto",
    "path": "/4",
    "imageUrl": "./image/glasses/glasses3.png"
  }
]